solidlab_perftest_common/agent.py
solidlab_perftest_common/content_types.py
solidlab_perftest_common/pagination.py
solidlab_perftest_common/status.py
solidlab_perftest_common/testenv.py
solidlab_perftest_common/upload_artifact.py
solidlab_perftest_common/util.py
solidlab_perftest_common-4.0.2.dist-info/LICENSE
solidlab_perftest_common-4.0.2.dist-info/METADATA
solidlab_perftest_common-4.0.2.dist-info/WHEEL
solidlab_perftest_common-4.0.2.dist-info/top_level.txt
solidlab_perftest_common-4.0.2.dist-info/RECORD
