Metadata-Version: 2.1
Name: solidlab-perftest-common
Version: 4.0.2
Summary: SolidLab PerfTest Common
Home-page: https://github.com/SolidLabResearch/solidlab-perftest-common
Author: Wim Van de Meerssche
Author-email: wim.vandemeerssche@imec.be
License: EUPL-1.2
Classifier: License :: OSI Approved :: European Union Public Licence 1.2 (EUPL 1.2)
Classifier: Programming Language :: Python :: 3 :: Only
Requires-Python: >=3.7
License-File: LICENSE
Requires-Dist: python-dateutil
Requires-Dist: requests
Requires-Dist: pydantic <2.0.0,>=1.10.13
